{
  "1750323349209": [
    {
      "userId": "user002",
      "name": "이불합",
      "age": "26",
      "email": "lee2@example.com",
      "stack": "Python, Flask",
      "intro": "도전 정신이 강합니다.",
      "reason": "관심 있는 분야라서 지원했습니다.",
      "github": "https://github.com/user002",
      "status": "불합격"
    },
    {
      "userId": "user003",
      "name": "박대기",
      "age": "23",
      "email": "park3@example.com",
      "stack": "React, Node.js",
      "intro": "웹 프론트엔드에 관심 많습니다.",
      "reason": "경험을 쌓고 싶습니다.",
      "github": "",
      "status": "불합격"
    },
    {
      "userId": "user004",
      "name": "최합격",
      "age": "28",
      "email": "choi4@example.com",
      "stack": "Vue.js, Django",
      "intro": "빠르게 배우고 잘합니다.",
      "reason": "프로젝트 경험을 얻고 싶습니다.",
      "github": "https://github.com/user004",
      "status": "불합격"
    },
    {
      "userId": "user005",
      "name": "정대기",
      "age": "22",
      "email": "jung5@example.com",
      "stack": "C++, Unity",
      "intro": "게임 개발자 지망생입니다.",
      "reason": "팀 프로젝트를 해보고 싶어요.",
      "github": "",
      "status": "불합격"
    },
    {
      "userId": "user006",
      "name": "신지원",
      "age": "21",
      "email": "new6@example.com",
      "stack": "Go, Docker",
      "intro": "인프라 쪽에 관심이 많습니다.",
      "reason": "실제 운영환경을 경험하고 싶어요.",
      "github": "https://github.com/user006",
      "status": "불합격"
    }
  ],
  "1750267840294": [],
  "1750268392874": [],
  "1750272751699": [],
  "1750273262462": [],
  "1750273105218": []
}